CHANGELOG.md
LICENSE
MANIFEST.in
README.md
requirements.txt
setup.py
octobot_triangular_arbitrage.egg-info/PKG-INFO
octobot_triangular_arbitrage.egg-info/SOURCES.txt
octobot_triangular_arbitrage.egg-info/dependency_links.txt
octobot_triangular_arbitrage.egg-info/not-zip-safe
octobot_triangular_arbitrage.egg-info/requires.txt
octobot_triangular_arbitrage.egg-info/top_level.txt
tests/test_detector.py
triangular_arbitrage/__init__.py
triangular_arbitrage/detector.py