Metadata-Version: 2.4
Name: octobot_triangular_arbitrage
Version: 1.2.1
Summary: Triangular arbitrage by OctoBot
Home-page: https://github.com/Drakkar-Software/Triangular-Arbitrage
Author: Drakkar-Software
Author-email: contact@drakkar.software
Classifier: Development Status :: 5 - Production/Stable
Classifier: Operating System :: OS Independent
Classifier: Operating System :: MacOS :: MacOS X
Classifier: Operating System :: Microsoft :: Windows
Classifier: Operating System :: POSIX
Classifier: Programming Language :: Python :: 3.10
Requires-Python: >=3.10
License-File: LICENSE
Requires-Dist: ccxt
Requires-Dist: networkx[default]<3.5,>=3.4
Requires-Dist: OctoBot-Commons<1.10,>=1.9
Dynamic: author
Dynamic: author-email
Dynamic: classifier
Dynamic: description
Dynamic: description-content-type
Dynamic: home-page
Dynamic: license-file
Dynamic: requires-dist
Dynamic: requires-python
Dynamic: summary
